resumate
