Metadata-Version: 2.4
Name: resumate
Version: 0.1.2
Summary: Beautiful PDF resumes from YAML - for humans, not ATS
Home-page: https://github.com/chris17453/resumate/
Author: Charles Watkins
Author-email: chris@watkinslabs.com
License: MIT
Project-URL: Bug Tracker, https://github.com/chris17453/resumate/issues
Project-URL: Documentation, https://github.com/chris17453/resumate
Project-URL: Source Code, https://github.com/chris17453/resumate
Keywords: resume cv pdf yaml generator template beautiful professional
Classifier: Development Status :: 4 - Beta
Classifier: Intended Audience :: End Users/Desktop
Classifier: Topic :: Office/Business
Classifier: Topic :: Text Processing :: Markup
Classifier: License :: OSI Approved :: MIT License
Classifier: Operating System :: OS Independent
Classifier: Programming Language :: Python :: 3
Classifier: Programming Language :: Python :: 3.7
Classifier: Programming Language :: Python :: 3.8
Classifier: Programming Language :: Python :: 3.9
Classifier: Programming Language :: Python :: 3.10
Classifier: Programming Language :: Python :: 3.11
Classifier: Programming Language :: Python :: 3.12
Requires-Python: >=3.7
License-File: LICENSE
Requires-Dist: reportlab>=3.6.0
Requires-Dist: PyYAML>=5.4
Requires-Dist: svglib>=1.2.0
Requires-Dist: qrcode>=7.3
Requires-Dist: Pillow>=8.0.0
Requires-Dist: matplotlib>=3.3.0
Requires-Dist: numpy>=1.19.0
Requires-Dist: lxml>=4.6.0
Requires-Dist: importlib_resources>=5.0; python_version < "3.9"
Dynamic: author
Dynamic: author-email
Dynamic: classifier
Dynamic: description
Dynamic: description-content-type
Dynamic: home-page
Dynamic: keywords
Dynamic: license
Dynamic: license-file
Dynamic: project-url
Dynamic: requires-dist
Dynamic: requires-python
Dynamic: summary
